rdflib_sqlalchemy/__init__.py
rdflib_sqlalchemy/base.py
rdflib_sqlalchemy/constants.py
rdflib_sqlalchemy/sql.py
rdflib_sqlalchemy/statistics.py
rdflib_sqlalchemy/store.py
rdflib_sqlalchemy/tables.py
rdflib_sqlalchemy/termutils.py
rdflib_sqlalchemy/types.py
brickschema_rdflib_sqlalchemy-0.6.1.dist-info/LICENSE.txt
brickschema_rdflib_sqlalchemy-0.6.1.dist-info/METADATA
brickschema_rdflib_sqlalchemy-0.6.1.dist-info/WHEEL
brickschema_rdflib_sqlalchemy-0.6.1.dist-info/entry_points.txt
brickschema_rdflib_sqlalchemy-0.6.1.dist-info/top_level.txt
brickschema_rdflib_sqlalchemy-0.6.1.dist-info/RECORD
